setup.py
random_number_game/__init__.py
random_number_game/random_number_game.py
random_number_game.egg-info/PKG-INFO
random_number_game.egg-info/SOURCES.txt
random_number_game.egg-info/dependency_links.txt
random_number_game.egg-info/not-zip-safe
random_number_game.egg-info/top_level.txt