Metadata-Version: 1.0
Name: random-number-game
Version: 0.1
Summary: Game to guess a number
Home-page: UNKNOWN
Author: UNKNOWN
Author-email: UNKNOWN
License: UNKNOWN
Platform: UNKNOWN
